{
    "Home": {
        "data": {
            "9": {
                "id": 9,
                "name": "rca",
                "inputs": {
                    "input_1": {
                        "connections": []
                    },
                    "input_2": {
                        "connections": []
                    },
                    "input_3": {
                        "connections": []
                    },
                    "input_4": {
                        "connections": []
                    },
                    "input_5": {
                        "connections": []
                    },
                    "input_6": {
                        "connections": []
                    },
                    "input_7": {
                        "connections": []
                    },
                    "input_8": {
                        "connections": []
                    },
                    "input_9": {
                        "connections": []
                    },
                    "input_10": {
                        "connections": []
                    },
                    "input_11": {
                        "connections": []
                    },
                    "input_12": {
                        "connections": []
                    }
                },
                "outputs": {
                    "output_1": {
                        "connections": []
                    },
                    "output_2": {
                        "connections": []
                    },
                    "output_3": {
                        "connections": []
                    },
                    "output_4": {
                        "connections": []
                    },
                    "output_5": {
                        "connections": []
                    },
                    "output_6": {
                        "connections": []
                    },
                    "output_7": {
                        "connections": []
                    },
                    "output_8": {
                        "connections": [
                            {
                                "node": "10",
                                "output": "input_3"
                            }
                        ]
                    }
                }
            },
            "10": {
                "id": 10,
                "name": "rca",
                "inputs": {
                    "input_1": {
                        "connections": []
                    },
                    "input_2": {
                        "connections": []
                    },
                    "input_3": {
                        "connections": [
                            {
                                "node": "9",
                                "input": "output_8"
                            }
                        ]
                    },
                    "input_4": {
                        "connections": []
                    },
                    "input_5": {
                        "connections": []
                    },
                    "input_6": {
                        "connections": []
                    },
                    "input_7": {
                        "connections": []
                    },
                    "input_8": {
                        "connections": []
                    },
                    "input_9": {
                        "connections": []
                    },
                    "input_10": {
                        "connections": []
                    },
                    "input_11": {
                        "connections": []
                    },
                    "input_12": {
                        "connections": []
                    }
                },
                "outputs": {
                    "output_1": {
                        "connections": []
                    },
                    "output_2": {
                        "connections": []
                    },
                    "output_3": {
                        "connections": []
                    },
                    "output_4": {
                        "connections": []
                    },
                    "output_5": {
                        "connections": []
                    },
                    "output_6": {
                        "connections": []
                    },
                    "output_7": {
                        "connections": []
                    },
                    "output_8": {
                        "connections": []
                    }
                }
            }
        }
    },
    "rca": {
        "data": {
            "5": {
                "id": 5,
                "name": "fulladder",
                "inputs": {
                    "input_1": {
                        "connections": []
                    },
                    "input_2": {
                        "connections": []
                    },
                    "input_3": {
                        "connections": []
                    }
                },
                "outputs": {
                    "output_1": {
                        "connections": []
                    },
                    "output_2": {
                        "connections": [
                            {
                                "node": "6",
                                "output": "input_3"
                            }
                        ]
                    }
                }
            },
            "6": {
                "id": 6,
                "name": "fulladder",
                "inputs": {
                    "input_1": {
                        "connections": []
                    },
                    "input_2": {
                        "connections": []
                    },
                    "input_3": {
                        "connections": [
                            {
                                "node": "5",
                                "input": "output_2"
                            }
                        ]
                    }
                },
                "outputs": {
                    "output_1": {
                        "connections": []
                    },
                    "output_2": {
                        "connections": [
                            {
                                "node": "7",
                                "output": "input_3"
                            }
                        ]
                    }
                }
            },
            "7": {
                "id": 7,
                "name": "fulladder",
                "inputs": {
                    "input_1": {
                        "connections": []
                    },
                    "input_2": {
                        "connections": []
                    },
                    "input_3": {
                        "connections": [
                            {
                                "node": "6",
                                "input": "output_2"
                            }
                        ]
                    }
                },
                "outputs": {
                    "output_1": {
                        "connections": []
                    },
                    "output_2": {
                        "connections": [
                            {
                                "node": "8",
                                "output": "input_3"
                            }
                        ]
                    }
                }
            },
            "8": {
                "id": 8,
                "name": "fulladder",
                "inputs": {
                    "input_1": {
                        "connections": []
                    },
                    "input_2": {
                        "connections": []
                    },
                    "input_3": {
                        "connections": [
                            {
                                "node": "7",
                                "input": "output_2"
                            }
                        ]
                    }
                },
                "outputs": {
                    "output_1": {
                        "connections": []
                    },
                    "output_2": {
                        "connections": []
                    }
                }
            }
        }
    }
}